agentlite/__init__.py
agentlite/utils.py
agentlite/actions/BaseAction.py
agentlite/actions/InnerActions.py
agentlite/actions/__init__.py
agentlite/agent_prompts/BasePrompt.py
agentlite/agent_prompts/__init__.py
agentlite/agent_prompts/prompt_utils.py
agentlite/agents/ABCAgent.py
agentlite/agents/BaseAgent.py
agentlite/agents/ManagerAgent.py
agentlite/agents/__init__.py
agentlite/agents/agent_utils.py
agentlite/commons/AgentAct.py
agentlite/commons/TaskPackage.py
agentlite/commons/__init__.py
agentlite/llm/LLMConfig.py
agentlite/llm/__init__.py
agentlite/llm/agent_llms.py
agentlite/logging/__init__.py
agentlite/logging/base.py
agentlite/logging/streamlit_logger.py
agentlite/logging/terminal_logger.py
agentlite/logging/utils.py
agentlite/memory/AgentSTMemory.py
agentlite/memory/__init__.py
agentlite/memory/memory_utils.py
agentlite_llm-0.1.12.dist-info/LICENSE.txt
agentlite_llm-0.1.12.dist-info/METADATA
agentlite_llm-0.1.12.dist-info/WHEEL
agentlite_llm-0.1.12.dist-info/top_level.txt
agentlite_llm-0.1.12.dist-info/RECORD
