Metadata-Version: 2.1
Name: agentlite-llm
Version: 0.1.12
Summary: Light Library for Building LLM Agent System
Author: Zhiwei Liu
Author-email: zhiweiliu@salesforce.com
License: Apache License 2.0
Requires-Python: >=3.9
License-File: LICENSE.txt
Requires-Dist: langchain ==0.1.3
Requires-Dist: langchain-openai ==0.0.5
Requires-Dist: openai ==1.10
Requires-Dist: pydantic
Requires-Dist: numpy
Requires-Dist: pandas <2.0.0
Requires-Dist: wikipedia
Requires-Dist: duckduckgo-search
Requires-Dist: openmeteo-requests ==1.2.0
Requires-Dist: requests-cache ==1.2.0
Requires-Dist: retry-requests ==2.0.0
